{"version": "1", "message": "ERROR: Hidden Testcases server unreachable.", "problem_id": "ads2_m3_a1_1", "user_id": "jprasanthkumar28", "score": {"sample": {"0": {"execution_time": 0.19134259223937988, "passed": true}, "1": {"execution_time": 0.17212152481079102, "passed": true}, "2": {"execution_time": 0.18656301498413086, "passed": true}, "3": {"execution_time": 0.17128348350524902, "passed": true}, "4": {"execution_time": 0.2039940357208252, "passed": true}, "5": {"execution_time": 0.1704692840576172, "passed": true}, "6": {"execution_time": 0.18765473365783691, "passed": true}, "7": {"execution_time": 0.1748201847076416, "passed": true}}}, "check_style_score": "0/1"}